{"author":"RebarBotNava","data":{"alias":"arbored-fawning-crossbill","description":"## Finding (S3 — verified)\n`src/rebar/__init__.py` is a 1224-LOC god-facade (largest file), exempt from the size gate by filename pattern, with ~49 top-level defs mostly delegating to `_reads`/`_commands`/`_writes`.\n\nCitations: `src/rebar/__init__.py` (1224 LOC; 14-param `list_tickets` at :872 — the fat signature is handled by the TicketQuery ticket, not here).\n\n## Remediation\nRelocate the wrapper BODIES into their existing owning submodules; keep `__init__.py` as import-and-re-export only, preserving every `rebar.<name>` path. Split only along clusters that already hang together; do NOT create <100-LOC fragments. After the split, pin `__init__.py` to a ceiling row (see S1 ratchet ticket).\n\ncascade_flag: moves ~49 symbol DEFINITIONS (names re-exported) — check anything importing `rebar._<oldloc>` directly, star-imports, and `__all__`; verify `dir(rebar)` unchanged.\n\n## Acceptance Criteria\n- [ ] `__init__.py` is a re-export surface under the pinned ceiling; logic lives in topical submodules\n- [ ] All public `import rebar; rebar.<fn>` names resolve unchanged (dir(rebar) stable)\n- [ ] No file <100 LOC created by the split","id":"4532-bdb8-a2a6-4018","parent_id":"1d96-6bc8-9749-45b8","priority":2,"tags":["janitor"],"ticket_type":"task","title":"Thin the __init__.py god-facade behind its existing submodules"},"env_id":"ade0f2ef-51cc-45a2-bb97-c09846cd3df5","event_type":"CREATE","timestamp":1783456335404785001,"uuid":"abb796fd-6837-4dd4-bf16-dbd841a62cc8"}