{"author":"Joe Oakhart","data":{"alias":"keen-optic-candy","description":"Lints merge-to-main*.sh scripts under $PLUGIN_DIR/scripts/ that do not exist in this repo. Evidence: zero inbound references; git grep merge-to-main -> only this file + comment ticket_graph/_links.py:198.\n\n## Acceptance Criteria\n- [ ] git rm src/rebar/_engine/check-merge-tickets-dir.sh\n- [ ] _links.py:198 comment drops the merge-to-main-direct.sh mention\n- [ ] Full suite green","id":"f505-c747-e8ef-4a02","parent_id":"3c09-9176-9305-4033","priority":2,"tags":["audit-2026-06-09","dso-residue"],"ticket_type":"task","title":"Delete orphan: check-merge-tickets-dir.sh (+ stale merge-to-main citation in _links.py)"},"env_id":"ade0f2ef-51cc-45a2-bb97-c09846cd3df5","event_type":"CREATE","timestamp":1781063905090791000,"uuid":"6e776d1f-8c14-4f4e-ac0c-df5bbaf02f01"}
