{"author":"Joe Oakhart","author_email":"joeoakhart+bot@navapbc.com","data":{"file_impact":[{"path":"src/rebar/_commands/verify_authorship.py","reason":"verify-identity + --require-authenticated/--since + JSON report + grandfathering"},{"path":"src/rebar/_cli/__init__.py","reason":"intercept verify-identity + alias"},{"path":"src/rebar/_config_schema.py","reason":"identity.enforce_since"},{"path":"src/rebar/schemas/verify_identity_report.schema.json","reason":"report schema"},{"path":".github/workflows/verify-identity.yaml","reason":"CI merge-gate"}]},"env_id":"ade0f2ef-51cc-45a2-bb97-c09846cd3df5","event_type":"FILE_IMPACT","timestamp":1783901926497047001,"uuid":"b668fe61-ca7f-4efd-9944-29a2c37776d1"}