{"author":"Joe Oakhart","data":{"body":"Link-sync verification complete (empirical). VERDICT: link sync is NOT wired into the reconcile pipeline in either direction; client primitives also broken live.\n\nTest A (in-process, tests/integration/rebar_reconciler/test_link_sync.py): BOTH FAIL (desired-behavior TDD spec).\n- A1 outbound: compute_outbound_mutations emits links=[] for a local 'blocks' dep. OutboundMutation.links is hardcoded [] in both create & update branches; no _diff_links; local 'deps' (shape {target_id,relation,link_uuid}) is never read by the differ.\n- A2 inbound: compute_inbound_mutations emits NO link/relation change for a Jira issuelinks array. InboundMutation has no links field; _diff_jira_vs_local never inspects issuelinks.\n\nLive probe (tests/external/test_link_sync_live.py): set_relationship FAILS live because acli 'workitem link create' rejects --json (set_relationship passes --json at acli_graph.py:437). Without --json the link create succeeds. get_issue_links also parses the wrong key: live 'link list --json' returns {\"issueLinks\":[{id,outwardIssueKey,typeName}]} (camelCase 'issueLinks', flat shape) but get_issue_links parses 'issuelinks' and expects the REST {type:{name},outwardIssue:{key}} shape. So both SET and GET primitives are mismatched to actual ACLI output. All probe issues cleaned up (verified gone).\n\nruff: clean on both new files. Tests left red (not xfx) per instruction."},"env_id":"ade0f2ef-51cc-45a2-bb97-c09846cd3df5","event_type":"COMMENT","timestamp":1781498075505439000,"uuid":"8458a9b5-0224-46fd-8ac5-06df4b2665cf"}