{"author":"RebarBotNava","data":{"alias":"innovative-halfcrazed-monkey","description":"## Why\n`_mkdir_lock_is_stale` (`src/rebar/_store/lock.py:162-181`) has branches for read errors\n(`except OSError: return False`), missing separator, foreign host, non-int PID\n(`except ValueError: return False`), and live/dead PID. Existing tests cover dead/live/\nabsent/foreign-host, but **non-int PID, missing-`:`-separator, and owner-file read-error are\nuntested** (PARTIALLY-VALIDATED: a real partial-branch coverage gap). The safety property is\nconservative — none may cause reclamation.\n\n## What\nAdd table-driven cases for the malformed/unreadable owner-file forms.\n\n## Scope\n- `tests/unit/test_lock_stale_reclaim.py`.\n\n## Acceptance Criteria\n- [ ] Cases: empty owner file; missing colon; empty host or PID; non-numeric PID; negative\n      PID; extra delimiters; unreadable owner file; owner file replaced while read.\n- [ ] Every case is conservative: no reclamation occurs.\n- [ ] `make test` green.","id":"2202-923d-dbb7-49a6","parent_id":"bf50-2131-271b-4fdc","priority":3,"tags":["p3","concurrency","lock"],"ticket_type":"story","title":"Add table-driven mkdir-lock malformed ownership-stamp tests"},"env_id":"ade0f2ef-51cc-45a2-bb97-c09846cd3df5","event_type":"CREATE","timestamp":1783784835407183001,"uuid":"fe5d07db-c0a2-4b60-8eab-bbb1e513dd27"}