{"author":"RebarBotNava","data":{"alias":"ornery-terrazzo-weevil","description":"## Why\n\nAudit Reliability finding #4 (MEDIUM). In src/rebar/_store/event_append.py:137-148, when git add or an unhealable git commit fails, cleanup only unlinks the worktree file — the blob stays **staged**, so the *next* successful write (which commits the whole index) durably commits the failed write's phantom event. The claim/transition path already fixed this exact bug (_unstage in _commands/txn.py:439, \"drop index (not just disk)\"); the general append path never got the fix. Related (audit 2.2): git commit runs before git add's return code is checked, so a failed add can still commit unrelated staged residue under this write's message.\n\n## What\n\nMirror txn.py in src/rebar/_store/event_append.py: on failure, git reset -q -- <relpath> in addition to unlinking; and check the add return code before invoking commit. Add a regression test that injects a commit failure, performs a subsequent successful write, and asserts the failed event is neither committed nor replayed. Consider a cheap fsck check for staged-index residue in the tracker (audit fsck-gap note).\n\n## Scope\n\nIn: src/rebar/_store/event_append.py failure path, tests. Out: txn.py (already correct), broader fsck redesign.\n\n## Acceptance Criteria\n\n- [ ] On stage/commit failure the event is removed from the index (git reset) as well as disk\n- [ ] git add's return code is checked before git commit runs\n- [ ] Regression test: injected commit failure followed by a successful write — the store contains only the successful event; replay and fsck are clean\n- [ ] make test green","id":"0e59-9be5-b86d-4e0b","parent_id":"d6a0-743b-71f9-4a5a","priority":2,"tags":[],"ticket_type":"task","title":"event_append: unstage the staged event on stage_and_commit failure (and check git add before commit)"},"env_id":"ade0f2ef-51cc-45a2-bb97-c09846cd3df5","event_type":"CREATE","timestamp":1783541082275414001,"uuid":"478dbdaf-5420-4182-bc67-fc771f4d6c69"}