{"author":"Joe Oakhart","data":{"alias":"worm-burr-fly","description":"## Why\nlist-epics duplicates query/reduction logic that belongs in the generic list primitive. Generalize the generic filters so 'get epics' is one generic call, then reduce list-epics to a thin deprecating wrapper. Orthogonal to the bash->Python strangler-fig (adult-oxide-slave) — tracked on its own.\n\n## What\n1. Expand the generic 'list' read primitive (rebar._engine_support.reads.list_states + ticket_reads CLI + library list_tickets + MCP list tool):\n   - --min-children=N : tickets with >= N non-deleted direct children.\n   - --unblocked / --blocked : filter by blocking state (reuse rebar.graph find_ready_tickets / all_blockers_closed).\n   - include a children_count field in list output (cheap, additive, universal) so one call returns enriched epics.\n2. list-epics becomes a thin wrapper: (a) display deprecation warning (stderr), (b) ONE call to get epics (generic list --type=epic --status=open,in_progress [--unblocked] [--min-children]), (c) ONE call to get P0 bugs (generic list --type=bug --priority=0, counted), (d) assemble the {p0_bugs, epics} output. Replaces the bespoke ticket-list-epics.sh reduction.\n3. Surfaces: CLI dispatcher arm, library list_epics(), MCP list_epics tool — all wrap + warn.\n\n## Acceptance Criteria\n- [ ] generic list gains --min-children + --unblocked/--blocked + children_count, at CLI + library + MCP\n- [ ] new filters/field covered by tests; list output schema updated for children_count\n- [ ] list-epics is a wrapper: warns + 1 call epics + 1 call P0 bugs -> {p0_bugs, epics}; no bespoke reduction\n- [ ] deprecation warning at CLI (stderr, not stdout/JSON) + library (DeprecationWarning) + MCP description\n- [ ] list-epics output parity preserved ({p0_bugs, epics}); existing schema/MCP tests green or updated\n- [ ] docs note the deprecation + new generic filters","id":"7e0b-3f12-d35f-4e33","parent_id":"","priority":2,"tags":[],"ticket_type":"story","title":"Generalize list filters + deprecate list-epics to a thin wrapper (orthogonal to strangler-fig)"},"env_id":"ade0f2ef-51cc-45a2-bb97-c09846cd3df5","event_type":"CREATE","timestamp":1781285001286612000,"uuid":"a055e783-9684-4f46-9a22-04009f45e1c7"}
