{"author":"Joe Oakhart","data":{"alias":"rite-bile-slate","description":"## Summary\n_has_rebar_id_label (binding_walk.py) matches ANY label with the rebar-id:/rebar-id- PREFIX, including a malformed empty 'rebar-id:' (no local id). The L10 adopt guard then stands down (treats it as identity-bound) and defers to binding-recovery — but with an empty id there is nothing to re-link, so the key is never adopted AND never bound, and bridge-fsck reports it as unbound_jira on every run. Surfaced by REB-659 (a manual 'assignee clobber' experiment carrying label 'rebar-id:'), which produced a perpetual bare-forge-tapir drift alert.\n\n## Reproduction Steps\n1. A Jira issue has label 'rebar-id:' (empty value) and no binding-store entry.\n2. Run the binding walk / bridge-fsck.\n3. The issue is neither adopted (L10 stands down) nor bound → perpetual unbound_jira drift.\n\n## Expected vs Actual\n- Expected: an empty/malformed rebar-id: marker is treated as UNMARKED (adoptable), so the key adopts (create+bind) normally.\n- Actual: the empty marker counts as a binding marker → adoption stands down → the key is stranded.\n\n## Acceptance Criteria\n- [ ] _has_rebar_id_label returns True only for a WELL-FORMED marker (non-empty id after the prefix).\n- [ ] A key with an empty 'rebar-id:' label is adopted (inbound create); a well-formed 'rebar-id:<id>' still stands down (no double-bind).\n- [ ] Regression test in tests/unit/rebar_reconciler/test_binding_walk.py; reconciler suite green.","id":"dec2-1232-de64-4e14","parent_id":"","priority":2,"tags":[],"ticket_type":"bug","title":"reconciler: malformed empty rebar-id: marker traps a Jira issue in unbound-drift limbo"},"env_id":"ade0f2ef-51cc-45a2-bb97-c09846cd3df5","event_type":"CREATE","timestamp":1783298825351200001,"uuid":"60ba4f15-1241-478e-9918-e9ddc1fbc03c"}