{"author":"Joe Oakhart","author_email":"joeoakhart+bot@navapbc.com","author_id":"594c-9dcf-5ad6-4e6d","data":{"body":"PREREQ VERIFIED (subagent): ba33 read layer + enriched fields landed on main. Data contract for the UI: rebar.audit.read.audit_trail(ticket_id) -> {ticket, plan_reviews[] (newest-first v2 payloads: findings[] with finding/criteria/location/evidence/scenarios/impact/suggested_fix/verification/validity/priority/decision/reason/block_threshold/blocking_enabled; coaching[] {move_id,finding_refs,...}; verdict/model/metrics/coverage/material_fingerprint), completion {attestation, sidecar{criteria[] of {criterion,met,citation,kind kind in codebase-verifiable|operator-attested}}}, code_reviews[] [{ticket_id, sidecars[] code_review_result_v2 with blocking/advisory/dropped/indeterminate buckets + coaching}]}. Read layer is best-effort/never-raises; legacy rounds may lack v2 fields (guard None). reviewbot stack = src/rebar/review_bot/app.py (FastAPI lazy-imported at app.py top only; extra 'reviewbot'=[fastapi,uvicorn[standard],boto3]). EPIC 2141 CLAIMED (in_progress)."},"env_id":"ade0f2ef-51cc-45a2-bb97-c09846cd3df5","event_type":"COMMENT","timestamp":1784088173676354001,"uuid":"d0947d6a-2b91-40df-b41a-32e5c762edae"}