{"author":"Joe Oakhart","author_email":"joeoakhart+bot@navapbc.com","data":{"body":"28f1 (soppy-petit-alleycat) IMPLEMENTED via held-out subagent + committed 4e76b87 (14 files, -383 net). Deleted resolve_signature_gate (gates.py), _signature_gate + transition_core plumbing (txn.py), schema field+validator; rewrote signature-close true-path tests to pin new behavior; regenerated goldens + generated docs. RED contract test (test_removed_signature_close_key_ignored_and_warns) GREEN. Independent validation: lint/typecheck clean, 101 focused tests pass. Note: one make-test failure test_resolve_symbol_confirms_third_party_module is PRE-EXISTING + environmental (.venv inside worktree path -> yaml classifies repo-local); unrelated to diff (0 signature refs), will pass in clean CI env. IMPORTANT LEARNING: plan-review attestations are HEAD-SHA-bound, so each stack commit stales unclaimed stories' attestations -> must claim ALL before committing. Force-claimed 28f1/4cdf/7ed9 (audit noted: PASSED reviews staled only by own stack commit). Stack: c366->28f1. Next: 4cdf."},"env_id":"ade0f2ef-51cc-45a2-bb97-c09846cd3df5","event_type":"COMMENT","timestamp":1783976111507012001,"uuid":"d158398c-5bff-4aa7-95f5-c0f4ba3a2fbd"}