{"author":"Joe Oakhart","data":{"body":"DONE (commit ee29e91a). Ported exists/resolve/format to rebar._engine_support.lookups, routed in-process via _LOOKUPS (full auto-init). Dual-run parity 18 scenarios green (all id forms, all format modes auto/canonical/alias/short/unknown-warn, miss/arity/empty); compacted-ticket SNAPSHOT fallback parity verified live (both return short prefix since alias read from CREATE only). interfaces tier 364 passed. CLI-only. No bash deleted."},"env_id":"ade0f2ef-51cc-45a2-bb97-c09846cd3df5","event_type":"COMMENT","timestamp":1781327007252305000,"uuid":"0e53559d-1b8f-4b29-8c93-b2324052716a"}