{"author":"Joe Oakhart","author_email":"joeoakhart+bot@navapbc.com","author_id":"594c-9dcf-5ad6-4e6d","data":{"fields":{"description":"## Why\n\nFlipping `identity.require_authenticated` with a wrong or self-referential `enforce_since`\nwould either fail the gate on legitimate historical unsigned events, or be impossible to pin\n(the boundary cannot be the flip commit that has not landed yet — a chicken-and-egg). This\nstory remediates the requirement check and **decides** the boundary anchor, but does **not**\nwrite it: the atomic-flip story writes `enforce_since` exactly once, so there is no\ndouble-write.\n\n## What\n\n- In `src/rebar/_commands/verify_authorship.py` and `src/rebar/_config_schema.py`, verify the\n  `enforce_since` grandfathering logic (pre-boundary events exempt; post-boundary in-scope\n  events enforced).\n- Add a regression test asserting the boundary behaviour in both directions.\n- **Decide and document** the enforcement-boundary anchor: an **existing** tickets-branch\n  commit at which signing is confirmed live across all writers (NOT the flip commit). Record\n  the chosen SHA + rationale on this ticket for the flip story to consume.\n\n## Scope\n\nThe grandfathering boundary check + a regression test + the boundary decision/rationale.\nWriting `enforce_since` into `rebar.toml` and the flag flip both belong to the atomic-flip\nstory — this story does **not** modify `rebar.toml`.\n\n## Acceptance Criteria\n\n- [ ] `rebar verify-identity` over the full history exits 0 with **zero** pre-boundary events\n      flagged, using the chosen anchor.\n- [ ] A regression test asserts: a synthetic **unsigned** event before the boundary PASSES,\n      and a new unsigned/forged in-scope event after the boundary FAILS. Proving command:\n      `make test` (the new test).\n- [ ] The enforcement-boundary anchor commit SHA is chosen (an existing tickets-branch commit,\n      not the flip commit) and its rationale recorded on this ticket. `rebar.toml` is NOT\n      modified by this story."}},"env_id":"ade0f2ef-51cc-45a2-bb97-c09846cd3df5","event_type":"EDIT","timestamp":1784228118988498001,"uuid":"0f0ed287-d239-4c01-9281-b196e7a3ae8d"}